{
	"easycom": {
		"^u-(.*)": "@/uview-ui/components/u-$1/u-$1.vue"
	},
	"pages": [ //pages数组中第一项表示应用启动页，参考：https://uniapp.dcloud.io/collocation/pages
		{
			"path": "pages/home/index",
			"style": {
				"app-plus":{
					// 将回弹属性关掉
					"bounce":"none",
					"titleNView":false
				}
			}
		},{
            "path" : "pages/villagehandle/index",
            "style" : {
				"app-plus":{
					// 将回弹属性关掉
					"bounce":"none",
					"titleNView":false
				}
			}
        },{
            "path" : "pages/wantosay/index",
            "style" : {
				"app-plus":{
					// 将回弹属性关掉
					"bounce":"none",
					"titleNView":false
				}
			}
        },{
            "path" : "pages/villagetalk/index",
            "style" : {
				"app-plus":{
					// 将回弹属性关掉
					"bounce":"none",
					"titleNView":false
				}
			}
        },{
            "path" : "pages/mine/index",
            "style" : {
				"app-plus":{
					// 将回弹属性关掉
					"bounce":"none",
					"titleNView":false
				}
			}
        }
    ],
	"globalStyle": {
		"navigationBarTextStyle": "black",
		"navigationBarTitleText": "uni-app",
		"navigationBarBackgroundColor": "#F8F8F8",
		"backgroundColor": "#F8F8F8"
	},
	"tabBar": {
	    "color": "#666",
	    "selectedColor": "#666",
	    "borderStyle": "black",
	    "backgroundColor": "#ffffff",
	    "list": [{
	        "pagePath": "pages/home/index",
	        "iconPath": "static/icon/xiaoxi.png",
	        "selectedIconPath": "static/icon/xiaoxi1.png",
	        "text": "首页"
	    }, {
	        "pagePath": "pages/villagehandle/index",
	        "iconPath": "static/icon/haoyou.png",
	        "selectedIconPath": "static/icon/haoyou1.png",
	        "text": "村里办"
	    },{
	        "pagePath": "pages/wantosay/index",
	        "iconPath": "static/icon/qun.png",
	        "selectedIconPath": "static/icon/qun1.png",
	        "text": "我要说"
	    },{
	        "pagePath": "pages/villagetalk/index",
	        "iconPath": "static/icon/grzx.png",
	        "selectedIconPath": "static/icon/grzx1.png",
	        "text": "村里聊"
	    },{
	        "pagePath": "pages/mine/index",
	        "iconPath": "static/icon/grzx.png",
	        "selectedIconPath": "static/icon/grzx1.png",
	        "text": "我的"
	    }]
	}
}
